{
  "parse": [
    {
      "V119983": {
        "id": "V119983",
        "indicator": "SPEECHACT",
        "type": "SA_TELL",
        "word": null,
        "roles": {
          "PUNCTYPE": "DECL",
          "CONTENT": "#V119750",
          "LEX": "WERE"
        },
        "start": 0,
        "end": 35
      },
      "V119750": {
        "id": "V119750",
        "indicator": "F",
        "type": "BE",
        "word": "BE",
        "roles": {
          "NEUTRAL": "#V119742",
          "NEUTRAL1": "#V119802",
          "TENSE": "PAST",
          "LEX": "WERE",
          "WNSENSE": "be%2:42:06::"
        },
        "start": 0,
        "end": 35
      },
      "V119742": {
        "id": "V119742",
        "indicator": "PRO-SET",
        "type": "REFERENTIAL-SEM",
        "word": "THEY",
        "roles": {
          "PROFORM": "THEY",
          "LEX": "THEY",
          "WNSENSE": "entity%1:03:00",
          "COREF": "#V119824"
        },
        "start": 0,
        "end": 5
      },
      "V119802": {
        "id": "V119802",
        "indicator": "A",
        "type": "FAMILY-GROUP",
        "word": "FAMILY",
        "roles": {
          "MOD": "#V119819",
          "LEX": "FAMILY",
          "WNSENSE": "family%1:14:02::"
        },
        "start": 10,
        "end": 35
      },
      "V119819": {
        "id": "V119819",
        "indicator": "F",
        "type": "APPRECIATE",
        "word": "LOVE",
        "roles": {
          "EXPERIENCER": "#V119802",
          "NEUTRAL": "#V119824",
          "TENSE": "PAST",
          "LEX": "LOVED",
          "WNSENSE": "love%2:37:00::"
        },
        "start": 19,
        "end": 35
      },
      "V119824": {
        "id": "V119824",
        "indicator": "INDEF-SET",
        "type": "GAME",
        "word": "GAME",
        "roles": {
          "LEX": "GAMES",
          "WNSENSE": "game%1:04:00::"
        },
        "start": 30,
        "end": 35
      },
      "root": "#V119983"
    }
  ],
  "alternatives": [
    [
      {
        "V120156": {
          "id": "V120156",
          "indicator": "SPEECHACT",
          "type": "SA_TELL",
          "word": null,
          "roles": {
            "PUNCTYPE": "DECL",
            "CONTENT": "#V119750",
            "LEX": "WERE"
          },
          "start": 0,
          "end": 36
        },
        "V119750": {
          "id": "V119750",
          "indicator": "F",
          "type": "BE",
          "word": "BE",
          "roles": {
            "NEUTRAL": "#V119742",
            "NEUTRAL1": "#V119802",
            "TENSE": "PAST",
            "LEX": "WERE",
            "WNSENSE": "be%2:42:06::"
          },
          "start": 0,
          "end": 35
        },
        "V119742": {
          "id": "V119742",
          "indicator": "PRO-SET",
          "type": "REFERENTIAL-SEM",
          "word": "THEY",
          "roles": {
            "PROFORM": "THEY",
            "LEX": "THEY",
            "WNSENSE": "entity%1:03:00"
          },
          "start": 0,
          "end": 5
        },
        "V119802": {
          "id": "V119802",
          "indicator": "BARE",
          "type": "FAMILY-GROUP",
          "word": "FAMILY",
          "roles": {
            "ASSOC-WITH": "#V119777",
            "MOD": "#V119819",
            "LEX": "FAMILY",
            "WNSENSE": "family%1:14:02::"
          },
          "start": 10,
          "end": 35
        },
        "V119777": {
          "id": "V119777",
          "indicator": "THE",
          "type": "LETTER-SYMBOL",
          "word": null,
          "roles": {
            "NAME-OF": "A",
            "LEX": "A",
            "WNSENSE": "a%1:10:00::"
          },
          "start": 10,
          "end": 12
        },
        "V119819": {
          "id": "V119819",
          "indicator": "F",
          "type": "APPRECIATE",
          "word": "LOVE",
          "roles": {
            "EXPERIENCER": "#V119802",
            "NEUTRAL": "#V119824",
            "TENSE": "PAST",
            "LEX": "LOVED",
            "WNSENSE": "love%2:37:00::"
          },
          "start": 19,
          "end": 35
        },
        "V119824": {
          "id": "V119824",
          "indicator": "INDEF-SET",
          "type": "GAME",
          "word": "GAME",
          "roles": {
            "LEX": "GAMES",
            "WNSENSE": "game%1:04:00::"
          },
          "start": 30,
          "end": 35
        },
        "root": "#V120156"
      }
    ],
    [
      {
        "V120207": {
          "id": "V120207",
          "indicator": "SPEECHACT",
          "type": "SA_TELL",
          "word": null,
          "roles": {
            "PUNCTYPE": "DECL",
            "CONTENT": "#V119750",
            "LEX": "WERE"
          },
          "start": 0,
          "end": 36
        },
        "V119750": {
          "id": "V119750",
          "indicator": "F",
          "type": "BE",
          "word": "BE",
          "roles": {
            "NEUTRAL": "#V119742",
            "NEUTRAL1": "#V119802",
            "TENSE": "PAST",
            "LEX": "WERE",
            "WNSENSE": "be%2:42:06::"
          },
          "start": 0,
          "end": 35
        },
        "V119742": {
          "id": "V119742",
          "indicator": "PRO-SET",
          "type": "REFERENTIAL-SEM",
          "word": "THEY",
          "roles": {
            "PROFORM": "THEY",
            "LEX": "THEY",
            "WNSENSE": "entity%1:03:00"
          },
          "start": 0,
          "end": 5
        },
        "V119802": {
          "id": "V119802",
          "indicator": "BARE",
          "type": "FAMILY-GROUP",
          "word": "FAMILY",
          "roles": {
            "ASSOC-WITH": "#V120072",
            "MOD": "#V119819",
            "LEX": "FAMILY",
            "WNSENSE": "family%1:14:02::"
          },
          "start": 10,
          "end": 35
        },
        "V120072": {
          "id": "V120072",
          "indicator": "THE",
          "type": "TIME-LOC",
          "word": null,
          "roles": {
            "DAY-OF-WEEK": "#V120056",
            "LEX": "A"
          },
          "start": 10,
          "end": 12
        },
        "V120056": {
          "id": "V120056",
          "indicator": "THE",
          "type": "SEQUENCE",
          "word": null,
          "roles": {
            "NAME-OF": "(A)",
            "VAL": "(A)",
            "LEX": "A"
          },
          "start": 10,
          "end": 12
        },
        "V119819": {
          "id": "V119819",
          "indicator": "F",
          "type": "APPRECIATE",
          "word": "LOVE",
          "roles": {
            "EXPERIENCER": "#V119802",
            "NEUTRAL": "#V119824",
            "TENSE": "PAST",
            "LEX": "LOVED",
            "WNSENSE": "love%2:37:00::"
          },
          "start": 19,
          "end": 35
        },
        "V119824": {
          "id": "V119824",
          "indicator": "INDEF-SET",
          "type": "GAME",
          "word": "GAME",
          "roles": {
            "LEX": "GAMES",
            "WNSENSE": "game%1:04:00::"
          },
          "start": 30,
          "end": 35
        },
        "root": "#V120207"
      }
    ],
    [
      {
        "V120610": {
          "id": "V120610",
          "indicator": "SPEECHACT",
          "type": "SA_TELL",
          "word": null,
          "roles": {
            "PUNCTYPE": "DECL",
            "CONTENT": "#V119750",
            "LEX": "WERE"
          },
          "start": 0,
          "end": 36
        },
        "V119750": {
          "id": "V119750",
          "indicator": "F",
          "type": "BE",
          "word": "BE",
          "roles": {
            "NEUTRAL": "#V119742",
            "NEUTRAL1": "#V119824",
            "TENSE": "PAST",
            "LEX": "WERE",
            "WNSENSE": "be%2:42:06::"
          },
          "start": 0,
          "end": 35
        },
        "V119742": {
          "id": "V119742",
          "indicator": "PRO-SET",
          "type": "REFERENTIAL-SEM",
          "word": "THEY",
          "roles": {
            "PROFORM": "THEY",
            "LEX": "THEY",
            "WNSENSE": "entity%1:03:00"
          },
          "start": 0,
          "end": 5
        },
        "V119824": {
          "id": "V119824",
          "indicator": "INDEF-SET",
          "type": "GAME",
          "word": "GAME",
          "roles": {
            "ASSOC-WITH": "#V119802",
            "LEX": "GAMES",
            "WNSENSE": "game%1:04:00::"
          },
          "start": 10,
          "end": 35
        },
        "V119802": {
          "id": "V119802",
          "indicator": "KIND",
          "type": "FAMILY-GROUP",
          "word": "FAMILY",
          "roles": {
            "ASSOC-WITH": "#V119777",
            "MOD": "#V119819",
            "LEX": "FAMILY",
            "WNSENSE": "family%1:14:02::"
          },
          "start": 10,
          "end": 35
        },
        "V119777": {
          "id": "V119777",
          "indicator": "THE",
          "type": "LETTER-SYMBOL",
          "word": null,
          "roles": {
            "NAME-OF": "A",
            "LEX": "A",
            "WNSENSE": "a%1:10:00::"
          },
          "start": 10,
          "end": 12
        },
        "V119819": {
          "id": "V119819",
          "indicator": "F",
          "type": "APPRECIATE",
          "word": "LOVE",
          "roles": {
            "EXPERIENCER": "#V119810",
            "NEUTRAL": "#V119802",
            "TENSE": "PAST",
            "LEX": "LOVED",
            "WNSENSE": "love%2:37:00::"
          },
          "start": 19,
          "end": 30
        },
        "V119810": {
          "id": "V119810",
          "indicator": "PRO",
          "type": "REFERENTIAL-SEM",
          "word": "THAT",
          "roles": {
            "PROFORM": "THAT",
            "LEX": "THAT",
            "WNSENSE": "entity%1:03:00"
          },
          "start": 19,
          "end": 24
        },
        "root": "#V120610"
      }
    ],
    [
      {
        "V120718": {
          "id": "V120718",
          "indicator": "SPEECHACT",
          "type": "SA_TELL",
          "word": null,
          "roles": {
            "PUNCTYPE": "DECL",
            "CONTENT": "#V119750",
            "LEX": "WERE"
          },
          "start": 0,
          "end": 36
        },
        "V119750": {
          "id": "V119750",
          "indicator": "F",
          "type": "BE",
          "word": "BE",
          "roles": {
            "NEUTRAL": "#V119742",
            "NEUTRAL1": "#V119824",
            "TENSE": "PAST",
            "LEX": "WERE",
            "WNSENSE": "be%2:42:06::"
          },
          "start": 0,
          "end": 35
        },
        "V119742": {
          "id": "V119742",
          "indicator": "PRO-SET",
          "type": "REFERENTIAL-SEM",
          "word": "THEY",
          "roles": {
            "PROFORM": "THEY",
            "LEX": "THEY",
            "WNSENSE": "entity%1:03:00"
          },
          "start": 0,
          "end": 5
        },
        "V119824": {
          "id": "V119824",
          "indicator": "INDEF-SET",
          "type": "GAME",
          "word": "GAME",
          "roles": {
            "ASSOC-WITH": "#V119802",
            "LEX": "GAMES",
            "WNSENSE": "game%1:04:00::"
          },
          "start": 10,
          "end": 35
        },
        "V119802": {
          "id": "V119802",
          "indicator": "KIND",
          "type": "FAMILY-GROUP",
          "word": "FAMILY",
          "roles": {
            "ASSOC-WITH": "#V120072",
            "MOD": "#V119819",
            "LEX": "FAMILY",
            "WNSENSE": "family%1:14:02::"
          },
          "start": 10,
          "end": 35
        },
        "V120072": {
          "id": "V120072",
          "indicator": "THE",
          "type": "TIME-LOC",
          "word": null,
          "roles": {
            "DAY-OF-WEEK": "#V120056",
            "LEX": "A"
          },
          "start": 10,
          "end": 12
        },
        "V120056": {
          "id": "V120056",
          "indicator": "THE",
          "type": "SEQUENCE",
          "word": null,
          "roles": {
            "NAME-OF": "(A)",
            "VAL": "(A)",
            "LEX": "A"
          },
          "start": 10,
          "end": 12
        },
        "V119819": {
          "id": "V119819",
          "indicator": "F",
          "type": "APPRECIATE",
          "word": "LOVE",
          "roles": {
            "EXPERIENCER": "#V119810",
            "NEUTRAL": "#V119802",
            "TENSE": "PAST",
            "LEX": "LOVED",
            "WNSENSE": "love%2:37:00::"
          },
          "start": 19,
          "end": 30
        },
        "V119810": {
          "id": "V119810",
          "indicator": "PRO",
          "type": "REFERENTIAL-SEM",
          "word": "THAT",
          "roles": {
            "PROFORM": "THAT",
            "LEX": "THAT",
            "WNSENSE": "entity%1:03:00"
          },
          "start": 19,
          "end": 24
        },
        "root": "#V120718"
      }
    ],
    [
      {
        "V120556": {
          "id": "V120556",
          "indicator": "SPEECHACT",
          "type": "SA_TELL",
          "word": null,
          "roles": {
            "PUNCTYPE": "DECL",
            "CONTENT": "#V119750",
            "LEX": "WERE"
          },
          "start": 0,
          "end": 36
        },
        "V119750": {
          "id": "V119750",
          "indicator": "F",
          "type": "BE",
          "word": "BE",
          "roles": {
            "NEUTRAL": "#V119742",
            "NEUTRAL1": "#V119824",
            "TENSE": "PAST",
            "LEX": "WERE",
            "WNSENSE": "be%2:42:06::"
          },
          "start": 0,
          "end": 35
        },
        "V119742": {
          "id": "V119742",
          "indicator": "PRO-SET",
          "type": "REFERENTIAL-SEM",
          "word": "THEY",
          "roles": {
            "PROFORM": "THEY",
            "LEX": "THEY",
            "WNSENSE": "entity%1:03:00"
          },
          "start": 0,
          "end": 5
        },
        "V119824": {
          "id": "V119824",
          "indicator": "INDEF-SET",
          "type": "GAME",
          "word": "GAME",
          "roles": {
            "ASSOC-WITH": "#V119802",
            "LEX": "GAMES",
            "WNSENSE": "game%1:04:00::"
          },
          "start": 10,
          "end": 35
        },
        "V119802": {
          "id": "V119802",
          "indicator": "KIND",
          "type": "FAMILY-GROUP",
          "word": "FAMILY",
          "roles": {
            "MOD": "#V119819",
            "LEX": "FAMILY",
            "WNSENSE": "family%1:14:02::"
          },
          "start": 10,
          "end": 35
        },
        "V119777": {
          "id": "V119777",
          "indicator": "THE",
          "type": "LETTER-SYMBOL",
          "word": null,
          "roles": {
            "NAME-OF": "A",
            "LEX": "A",
            "WNSENSE": "a%1:10:00::"
          },
          "start": 10,
          "end": 12
        },
        "V119819": {
          "id": "V119819",
          "indicator": "F",
          "type": "APPRECIATE",
          "word": "LOVE",
          "roles": {
            "EXPERIENCER": "#V119810",
            "NEUTRAL": "#V119802",
            "TENSE": "PAST",
            "LEX": "LOVED",
            "WNSENSE": "love%2:37:00::"
          },
          "start": 19,
          "end": 30
        },
        "V119810": {
          "id": "V119810",
          "indicator": "PRO",
          "type": "REFERENTIAL-SEM",
          "word": "THAT",
          "roles": {
            "PROFORM": "THAT",
            "LEX": "THAT",
            "WNSENSE": "entity%1:03:00"
          },
          "start": 19,
          "end": 24
        },
        "root": "#V120556"
      }
    ],
    [
      {
        "V120670": {
          "id": "V120670",
          "indicator": "SPEECHACT",
          "type": "SA_TELL",
          "word": null,
          "roles": {
            "PUNCTYPE": "DECL",
            "CONTENT": "#V119750",
            "LEX": "WERE"
          },
          "start": 0,
          "end": 36
        },
        "V119750": {
          "id": "V119750",
          "indicator": "F",
          "type": "BE",
          "word": "BE",
          "roles": {
            "NEUTRAL": "#V119742",
            "NEUTRAL1": "#V119824",
            "TENSE": "PAST",
            "LEX": "WERE",
            "WNSENSE": "be%2:42:06::"
          },
          "start": 0,
          "end": 35
        },
        "V119742": {
          "id": "V119742",
          "indicator": "PRO-SET",
          "type": "REFERENTIAL-SEM",
          "word": "THEY",
          "roles": {
            "PROFORM": "THEY",
            "LEX": "THEY",
            "WNSENSE": "entity%1:03:00"
          },
          "start": 0,
          "end": 5
        },
        "V119824": {
          "id": "V119824",
          "indicator": "INDEF-SET",
          "type": "GAME",
          "word": "GAME",
          "roles": {
            "ASSOC-WITH": "#V119802",
            "LEX": "GAMES",
            "WNSENSE": "game%1:04:00::"
          },
          "start": 10,
          "end": 35
        },
        "V119802": {
          "id": "V119802",
          "indicator": "KIND",
          "type": "FAMILY-GROUP",
          "word": "FAMILY",
          "roles": {
            "MOD": "#V119819",
            "LEX": "FAMILY",
            "WNSENSE": "family%1:14:02::"
          },
          "start": 10,
          "end": 35
        },
        "V120072": {
          "id": "V120072",
          "indicator": "THE",
          "type": "TIME-LOC",
          "word": null,
          "roles": {
            "DAY-OF-WEEK": "#V120056",
            "LEX": "A"
          },
          "start": 10,
          "end": 12
        },
        "V120056": {
          "id": "V120056",
          "indicator": "THE",
          "type": "SEQUENCE",
          "word": null,
          "roles": {
            "NAME-OF": "(A)",
            "VAL": "(A)",
            "LEX": "A"
          },
          "start": 10,
          "end": 12
        },
        "V119819": {
          "id": "V119819",
          "indicator": "F",
          "type": "APPRECIATE",
          "word": "LOVE",
          "roles": {
            "EXPERIENCER": "#V119810",
            "NEUTRAL": "#V119802",
            "TENSE": "PAST",
            "LEX": "LOVED",
            "WNSENSE": "love%2:37:00::"
          },
          "start": 19,
          "end": 30
        },
        "V119810": {
          "id": "V119810",
          "indicator": "PRO",
          "type": "REFERENTIAL-SEM",
          "word": "THAT",
          "roles": {
            "PROFORM": "THAT",
            "LEX": "THAT",
            "WNSENSE": "entity%1:03:00"
          },
          "start": 19,
          "end": 24
        },
        "root": "#V120670"
      }
    ],
    [
      {
        "V120445": {
          "id": "V120445",
          "indicator": "SPEECHACT",
          "type": "SA_TELL",
          "word": null,
          "roles": {
            "PUNCTYPE": "DECL",
            "CONTENT": "#V119749",
            "LEX": "WERE"
          },
          "start": 0,
          "end": 36
        },
        "V119749": {
          "id": "V119749",
          "indicator": "F",
          "type": "HAVE-PROPERTY",
          "word": "BE",
          "roles": {
            "NEUTRAL": "#V119742",
            "FORMAL": "#V119988",
            "TENSE": "PAST",
            "LEX": "WERE",
            "WNSENSE": "be%2:42:03::"
          },
          "start": 0,
          "end": 35
        },
        "V119742": {
          "id": "V119742",
          "indicator": "PRO-SET",
          "type": "REFERENTIAL-SEM",
          "word": "THEY",
          "roles": {
            "PROFORM": "THEY",
            "LEX": "THEY",
            "WNSENSE": "entity%1:03:00"
          },
          "start": 0,
          "end": 5
        },
        "V119988": {
          "id": "V119988",
          "indicator": "F",
          "type": "MEMBERSHIP",
          "word": null,
          "roles": {
            "FIGURE": "#V119742",
            "GROUND": "#V119802",
            "LEX": "FAMILY"
          },
          "start": 10,
          "end": 35
        },
        "V119802": {
          "id": "V119802",
          "indicator": "THE-SET",
          "type": "FAMILY-GROUP",
          "word": "FAMILY",
          "roles": {
            "MOD": "#V119819"
          },
          "start": 10,
          "end": 35
        },
        "V119819": {
          "id": "V119819",
          "indicator": "F",
          "type": "APPRECIATE",
          "word": "LOVE",
          "roles": {
            "EXPERIENCER": "#V119802",
            "NEUTRAL": "#V119824",
            "TENSE": "PAST",
            "LEX": "LOVED",
            "WNSENSE": "love%2:37:00::"
          },
          "start": 19,
          "end": 35
        },
        "V119824": {
          "id": "V119824",
          "indicator": "INDEF-SET",
          "type": "GAME",
          "word": "GAME",
          "roles": {
            "LEX": "GAMES",
            "WNSENSE": "game%1:04:00::"
          },
          "start": 30,
          "end": 35
        },
        "root": "#V120445"
      }
    ],
    [
      {
        "V120837": {
          "id": "V120837",
          "indicator": "SPEECHACT",
          "type": "SA_TELL",
          "word": null,
          "roles": {
            "PUNCTYPE": "DECL",
            "CONTENT": "#V119750",
            "LEX": "WERE"
          },
          "start": 0,
          "end": 36
        },
        "V119750": {
          "id": "V119750",
          "indicator": "F",
          "type": "BE",
          "word": "BE",
          "roles": {
            "NEUTRAL": "#V119742",
            "NEUTRAL1": "#V119824",
            "BENEFICIARY": "#V119802",
            "TENSE": "PAST",
            "LEX": "WERE",
            "WNSENSE": "be%2:42:06::"
          },
          "start": 0,
          "end": 35
        },
        "V119742": {
          "id": "V119742",
          "indicator": "PRO-SET",
          "type": "REFERENTIAL-SEM",
          "word": "THEY",
          "roles": {
            "PROFORM": "THEY",
            "LEX": "THEY",
            "WNSENSE": "entity%1:03:00"
          },
          "start": 0,
          "end": 5
        },
        "V119802": {
          "id": "V119802",
          "indicator": "A",
          "type": "FAMILY-GROUP",
          "word": "FAMILY",
          "roles": {
            "MOD": "#V119819",
            "LEX": "FAMILY",
            "WNSENSE": "family%1:14:02::"
          },
          "start": 10,
          "end": 30
        },
        "V119819": {
          "id": "V119819",
          "indicator": "F",
          "type": "APPRECIATE",
          "word": "LOVE",
          "roles": {
            "EXPERIENCER": "#V119810",
            "NEUTRAL": "#V119802",
            "TENSE": "PAST",
            "LEX": "LOVED",
            "WNSENSE": "love%2:37:00::"
          },
          "start": 19,
          "end": 30
        },
        "V119810": {
          "id": "V119810",
          "indicator": "PRO",
          "type": "REFERENTIAL-SEM",
          "word": "THAT",
          "roles": {
            "PROFORM": "THAT",
            "LEX": "THAT",
            "WNSENSE": "entity%1:03:00"
          },
          "start": 19,
          "end": 24
        },
        "V119824": {
          "id": "V119824",
          "indicator": "INDEF-SET",
          "type": "GAME",
          "word": "GAME",
          "roles": {
            "LEX": "GAMES",
            "WNSENSE": "game%1:04:00::"
          },
          "start": 30,
          "end": 35
        },
        "root": "#V120837"
      }
    ],
    [
      {
        "V120861": {
          "id": "V120861",
          "indicator": "SPEECHACT",
          "type": "SA_TELL",
          "word": null,
          "roles": {
            "PUNCTYPE": "DECL",
            "CONTENT": "#V119749",
            "LEX": "WERE"
          },
          "start": 0,
          "end": 36
        },
        "V119749": {
          "id": "V119749",
          "indicator": "F",
          "type": "HAVE-PROPERTY",
          "word": "BE",
          "roles": {
            "NEUTRAL": "#V119742",
            "FORMAL": "#V120172",
            "TENSE": "PAST",
            "LEX": "WERE",
            "WNSENSE": "be%2:42:03::"
          },
          "start": 0,
          "end": 35
        },
        "V119742": {
          "id": "V119742",
          "indicator": "PRO-SET",
          "type": "REFERENTIAL-SEM",
          "word": "THEY",
          "roles": {
            "PROFORM": "THEY",
            "LEX": "THEY",
            "WNSENSE": "entity%1:03:00"
          },
          "start": 0,
          "end": 5
        },
        "V120172": {
          "id": "V120172",
          "indicator": "F",
          "type": "MEMBERSHIP",
          "word": null,
          "roles": {
            "FIGURE": "#V119742",
            "GROUND": "#V119802",
            "LEX": "FAMILY"
          },
          "start": 10,
          "end": 35
        },
        "V119802": {
          "id": "V119802",
          "indicator": "THE-SET",
          "type": "FAMILY-GROUP",
          "word": "FAMILY",
          "roles": {
            "ASSOC-WITH": "#V119777",
            "MOD": "#V119819"
          },
          "start": 10,
          "end": 35
        },
        "V119777": {
          "id": "V119777",
          "indicator": "THE",
          "type": "LETTER-SYMBOL",
          "word": null,
          "roles": {
            "NAME-OF": "A",
            "LEX": "A",
            "WNSENSE": "a%1:10:00::"
          },
          "start": 10,
          "end": 12
        },
        "V119819": {
          "id": "V119819",
          "indicator": "F",
          "type": "APPRECIATE",
          "word": "LOVE",
          "roles": {
            "EXPERIENCER": "#V119802",
            "NEUTRAL": "#V119824",
            "TENSE": "PAST",
            "LEX": "LOVED",
            "WNSENSE": "love%2:37:00::"
          },
          "start": 19,
          "end": 35
        },
        "V119824": {
          "id": "V119824",
          "indicator": "INDEF-SET",
          "type": "GAME",
          "word": "GAME",
          "roles": {
            "LEX": "GAMES",
            "WNSENSE": "game%1:04:00::"
          },
          "start": 30,
          "end": 35
        },
        "root": "#V120861"
      }
    ]
  ],
  "sentence": "They were a family that loved games.",
  "reparsed": [
    [
      {
        "V1930619": {
          "id": "V1930619",
          "indicator": "SPEECHACT",
          "type": "SA_TELL",
          "word": null,
          "roles": {
            "CONTENT": "#V1929860",
            "LEX": "WERE"
          },
          "start": 0,
          "end": 34
        },
        "V1929860": {
          "id": "V1929860",
          "indicator": "F",
          "type": "BE",
          "word": "BE",
          "roles": {
            "NEUTRAL": "#V1929852",
            "NEUTRAL1": "#V1929934",
            "TENSE": "PAST",
            "LEX": "WERE",
            "WNSENSE": "be%2:42:06::"
          },
          "start": 0,
          "end": 34
        },
        "V1929852": {
          "id": "V1929852",
          "indicator": "PRO-SET",
          "type": "REFERENTIAL-SEM",
          "word": "THEY",
          "roles": {
            "PROFORM": "THEY",
            "LEX": "THEY",
            "WNSENSE": "entity%1:03:00"
          },
          "start": 0,
          "end": 5
        },
        "V1929934": {
          "id": "V1929934",
          "indicator": "INDEF-SET",
          "type": "GAME",
          "word": "GAME",
          "roles": {
            "ASSOC-WITH": "#V1929912",
            "LEX": "GAMES",
            "WNSENSE": "game%1:04:00::"
          },
          "start": 10,
          "end": 34
        },
        "V1929912": {
          "id": "V1929912",
          "indicator": "KIND",
          "type": "FAMILY-GROUP",
          "word": "FAMILY",
          "roles": {
            "ASSOC-WITH": "#V1929887",
            "MOD": "#V1929929",
            "LEX": "FAMILY",
            "WNSENSE": "family%1:14:02::"
          },
          "start": 10,
          "end": 34
        },
        "V1929887": {
          "id": "V1929887",
          "indicator": "THE",
          "type": "LETTER-SYMBOL",
          "word": null,
          "roles": {
            "NAME-OF": "A",
            "LEX": "A",
            "WNSENSE": "a%1:10:00::"
          },
          "start": 10,
          "end": 12
        },
        "V1929929": {
          "id": "V1929929",
          "indicator": "F",
          "type": "APPRECIATE",
          "word": "LOVE",
          "roles": {
            "EXPERIENCER": "#V1929920",
            "NEUTRAL": "#V1929912",
            "TENSE": "PAST",
            "LEX": "LOVED",
            "WNSENSE": "love%2:37:00::"
          },
          "start": 19,
          "end": 30
        },
        "V1929920": {
          "id": "V1929920",
          "indicator": "PRO",
          "type": "REFERENTIAL-SEM",
          "word": "THAT",
          "roles": {
            "PROFORM": "THAT",
            "LEX": "THAT",
            "WNSENSE": "entity%1:03:00"
          },
          "start": 19,
          "end": 24
        },
        "root": "#V1930619"
      }
    ],
    [
      {
        "V1930669": {
          "id": "V1930669",
          "indicator": "SPEECHACT",
          "type": "SA_TELL",
          "word": null,
          "roles": {
            "CONTENT": "#V1929860",
            "LEX": "WERE"
          },
          "start": 0,
          "end": 35
        },
        "V1929860": {
          "id": "V1929860",
          "indicator": "F",
          "type": "BE",
          "word": "BE",
          "roles": {
            "NEUTRAL": "#V1929852",
            "NEUTRAL1": "#V1929934",
            "TENSE": "PAST",
            "LEX": "WERE",
            "WNSENSE": "be%2:42:06::"
          },
          "start": 0,
          "end": 35
        },
        "V1929852": {
          "id": "V1929852",
          "indicator": "PRO-SET",
          "type": "REFERENTIAL-SEM",
          "word": "THEY",
          "roles": {
            "PROFORM": "THEY",
            "LEX": "THEY",
            "WNSENSE": "entity%1:03:00"
          },
          "start": 0,
          "end": 5
        },
        "V1929934": {
          "id": "V1929934",
          "indicator": "INDEF-SET",
          "type": "GAME",
          "word": "GAME",
          "roles": {
            "ASSOC-WITH": "#V1929912",
            "LEX": "GAMES",
            "WNSENSE": "game%1:04:00::"
          },
          "start": 10,
          "end": 35
        },
        "V1929912": {
          "id": "V1929912",
          "indicator": "KIND",
          "type": "FAMILY-GROUP",
          "word": "FAMILY",
          "roles": {
            "ASSOC-WITH": "#V1930155",
            "MOD": "#V1929929",
            "LEX": "FAMILY",
            "WNSENSE": "family%1:14:02::"
          },
          "start": 10,
          "end": 35
        },
        "V1930155": {
          "id": "V1930155",
          "indicator": "THE",
          "type": "TIME-LOC",
          "word": null,
          "roles": {
            "DAY-OF-WEEK": "#V1930136",
            "LEX": "A"
          },
          "start": 10,
          "end": 12
        },
        "V1930136": {
          "id": "V1930136",
          "indicator": "THE",
          "type": "SEQUENCE",
          "word": null,
          "roles": {
            "NAME-OF": "(A)",
            "VAL": "(A)",
            "LEX": "A"
          },
          "start": 10,
          "end": 12
        },
        "V1929929": {
          "id": "V1929929",
          "indicator": "F",
          "type": "APPRECIATE",
          "word": "LOVE",
          "roles": {
            "EXPERIENCER": "#V1929920",
            "NEUTRAL": "#V1929912",
            "TENSE": "PAST",
            "LEX": "LOVED",
            "WNSENSE": "love%2:37:00::"
          },
          "start": 19,
          "end": 30
        },
        "V1929920": {
          "id": "V1929920",
          "indicator": "PRO",
          "type": "REFERENTIAL-SEM",
          "word": "THAT",
          "roles": {
            "PROFORM": "THAT",
            "LEX": "THAT",
            "WNSENSE": "entity%1:03:00"
          },
          "start": 19,
          "end": 24
        },
        "root": "#V1930669"
      }
    ],
    [
      {
        "V1930435": {
          "id": "V1930435",
          "indicator": "SPEECHACT",
          "type": "SA_TELL",
          "word": null,
          "roles": {
            "CONTENT": "#V1929860",
            "LEX": "WERE"
          },
          "start": 0,
          "end": 35
        },
        "V1929860": {
          "id": "V1929860",
          "indicator": "F",
          "type": "BE",
          "word": "BE",
          "roles": {
            "NEUTRAL": "#V1929852",
            "NEUTRAL1": "#V1929934",
            "TENSE": "PAST",
            "LEX": "WERE",
            "WNSENSE": "be%2:42:06::"
          },
          "start": 0,
          "end": 35
        },
        "V1929852": {
          "id": "V1929852",
          "indicator": "PRO-SET",
          "type": "REFERENTIAL-SEM",
          "word": "THEY",
          "roles": {
            "PROFORM": "THEY",
            "LEX": "THEY",
            "WNSENSE": "entity%1:03:00"
          },
          "start": 0,
          "end": 5
        },
        "V1929934": {
          "id": "V1929934",
          "indicator": "INDEF-SET",
          "type": "GAME",
          "word": "GAME",
          "roles": {
            "ASSOC-WITH1": "#V1929887",
            "ASSOC-WITH": "#V1929912",
            "LEX": "GAMES",
            "WNSENSE": "game%1:04:00::"
          },
          "start": 10,
          "end": 35
        },
        "V1929912": {
          "id": "V1929912",
          "indicator": "KIND",
          "type": "FAMILY-GROUP",
          "word": "FAMILY",
          "roles": {
            "MOD": "#V1929929",
            "LEX": "FAMILY",
            "WNSENSE": "family%1:14:02::"
          },
          "start": 10,
          "end": 35
        },
        "V1929887": {
          "id": "V1929887",
          "indicator": "THE",
          "type": "LETTER-SYMBOL",
          "word": null,
          "roles": {
            "NAME-OF": "A",
            "LEX": "A",
            "WNSENSE": "a%1:10:00::"
          },
          "start": 10,
          "end": 12
        },
        "V1929929": {
          "id": "V1929929",
          "indicator": "F",
          "type": "APPRECIATE",
          "word": "LOVE",
          "roles": {
            "EXPERIENCER": "#V1929920",
            "NEUTRAL": "#V1929912",
            "TENSE": "PAST",
            "LEX": "LOVED",
            "WNSENSE": "love%2:37:00::"
          },
          "start": 19,
          "end": 30
        },
        "V1929920": {
          "id": "V1929920",
          "indicator": "PRO",
          "type": "REFERENTIAL-SEM",
          "word": "THAT",
          "roles": {
            "PROFORM": "THAT",
            "LEX": "THAT",
            "WNSENSE": "entity%1:03:00"
          },
          "start": 19,
          "end": 24
        },
        "root": "#V1930435"
      }
    ],
    [
      {
        "V1930472": {
          "id": "V1930472",
          "indicator": "SPEECHACT",
          "type": "SA_TELL",
          "word": null,
          "roles": {
            "CONTENT": "#V1929860",
            "LEX": "WERE"
          },
          "start": 0,
          "end": 35
        },
        "V1929860": {
          "id": "V1929860",
          "indicator": "F",
          "type": "BE",
          "word": "BE",
          "roles": {
            "NEUTRAL": "#V1929852",
            "NEUTRAL1": "#V1929934",
            "TENSE": "PAST",
            "LEX": "WERE",
            "WNSENSE": "be%2:42:06::"
          },
          "start": 0,
          "end": 35
        },
        "V1929852": {
          "id": "V1929852",
          "indicator": "PRO-SET",
          "type": "REFERENTIAL-SEM",
          "word": "THEY",
          "roles": {
            "PROFORM": "THEY",
            "LEX": "THEY",
            "WNSENSE": "entity%1:03:00"
          },
          "start": 0,
          "end": 5
        },
        "V1929934": {
          "id": "V1929934",
          "indicator": "INDEF-SET",
          "type": "GAME",
          "word": "GAME",
          "roles": {
            "ASSOC-WITH1": "#V1930155",
            "ASSOC-WITH": "#V1929912",
            "LEX": "GAMES",
            "WNSENSE": "game%1:04:00::"
          },
          "start": 10,
          "end": 35
        },
        "V1929912": {
          "id": "V1929912",
          "indicator": "KIND",
          "type": "FAMILY-GROUP",
          "word": "FAMILY",
          "roles": {
            "MOD": "#V1929929",
            "LEX": "FAMILY",
            "WNSENSE": "family%1:14:02::"
          },
          "start": 10,
          "end": 35
        },
        "V1930155": {
          "id": "V1930155",
          "indicator": "THE",
          "type": "TIME-LOC",
          "word": null,
          "roles": {
            "DAY-OF-WEEK": "#V1930136",
            "LEX": "A"
          },
          "start": 10,
          "end": 12
        },
        "V1930136": {
          "id": "V1930136",
          "indicator": "THE",
          "type": "SEQUENCE",
          "word": null,
          "roles": {
            "NAME-OF": "(A)",
            "VAL": "(A)",
            "LEX": "A"
          },
          "start": 10,
          "end": 12
        },
        "V1929929": {
          "id": "V1929929",
          "indicator": "F",
          "type": "APPRECIATE",
          "word": "LOVE",
          "roles": {
            "EXPERIENCER": "#V1929920",
            "NEUTRAL": "#V1929912",
            "TENSE": "PAST",
            "LEX": "LOVED",
            "WNSENSE": "love%2:37:00::"
          },
          "start": 19,
          "end": 30
        },
        "V1929920": {
          "id": "V1929920",
          "indicator": "PRO",
          "type": "REFERENTIAL-SEM",
          "word": "THAT",
          "roles": {
            "PROFORM": "THAT",
            "LEX": "THAT",
            "WNSENSE": "entity%1:03:00"
          },
          "start": 19,
          "end": 24
        },
        "root": "#V1930472"
      }
    ],
    [
      {
        "V1930418": {
          "id": "V1930418",
          "indicator": "SPEECHACT",
          "type": "SA_TELL",
          "word": null,
          "roles": {
            "CONTENT": "#V1929859",
            "LEX": "WERE"
          },
          "start": 0,
          "end": 35
        },
        "V1929859": {
          "id": "V1929859",
          "indicator": "F",
          "type": "HAVE-PROPERTY",
          "word": "BE",
          "roles": {
            "NEUTRAL": "#V1929852",
            "FORMAL": "#V1930111",
            "TENSE": "PAST",
            "LEX": "WERE",
            "WNSENSE": "be%2:42:03::"
          },
          "start": 0,
          "end": 35
        },
        "V1929852": {
          "id": "V1929852",
          "indicator": "PRO-SET",
          "type": "REFERENTIAL-SEM",
          "word": "THEY",
          "roles": {
            "PROFORM": "THEY",
            "LEX": "THEY",
            "WNSENSE": "entity%1:03:00"
          },
          "start": 0,
          "end": 5
        },
        "V1930111": {
          "id": "V1930111",
          "indicator": "F",
          "type": "MEMBERSHIP",
          "word": null,
          "roles": {
            "FIGURE": "#V1929852",
            "GROUND": "#V1929912",
            "LEX": "FAMILY"
          },
          "start": 10,
          "end": 35
        },
        "V1929912": {
          "id": "V1929912",
          "indicator": "BARE",
          "type": "FAMILY-GROUP",
          "word": "FAMILY",
          "roles": {
            "MOD": "#V1929929"
          },
          "start": 10,
          "end": 35
        },
        "V1929929": {
          "id": "V1929929",
          "indicator": "F",
          "type": "APPRECIATE",
          "word": "LOVE",
          "roles": {
            "EXPERIENCER": "#V1929912",
            "NEUTRAL": "#V1929934",
            "TENSE": "PAST",
            "LEX": "LOVED",
            "WNSENSE": "love%2:37:00::"
          },
          "start": 19,
          "end": 35
        },
        "V1929934": {
          "id": "V1929934",
          "indicator": "INDEF-SET",
          "type": "GAME",
          "word": "GAME",
          "roles": {
            "LEX": "GAMES",
            "WNSENSE": "game%1:04:00::"
          },
          "start": 30,
          "end": 35
        },
        "root": "#V1930418"
      }
    ],
    [
      {
        "V1930521": {
          "id": "V1930521",
          "indicator": "SPEECHACT",
          "type": "SA_TELL",
          "word": null,
          "roles": {
            "CONTENT": "#V1929860",
            "LEX": "WERE"
          },
          "start": 0,
          "end": 35
        },
        "V1929860": {
          "id": "V1929860",
          "indicator": "F",
          "type": "BE",
          "word": "BE",
          "roles": {
            "NEUTRAL": "#V1929852",
            "NEUTRAL1": "#V1929934",
            "BENEFICIARY": "#V1929912",
            "TENSE": "PAST",
            "LEX": "WERE",
            "WNSENSE": "be%2:42:06::"
          },
          "start": 0,
          "end": 35
        },
        "V1929852": {
          "id": "V1929852",
          "indicator": "PRO-SET",
          "type": "REFERENTIAL-SEM",
          "word": "THEY",
          "roles": {
            "PROFORM": "THEY",
            "LEX": "THEY",
            "WNSENSE": "entity%1:03:00"
          },
          "start": 0,
          "end": 5
        },
        "V1929912": {
          "id": "V1929912",
          "indicator": "A",
          "type": "FAMILY-GROUP",
          "word": "FAMILY",
          "roles": {
            "LEX": "FAMILY",
            "WNSENSE": "family%1:14:02::"
          },
          "start": 10,
          "end": 19
        },
        "V1929934": {
          "id": "V1929934",
          "indicator": "INDEF-SET",
          "type": "GAME",
          "word": "GAME",
          "roles": {
            "MOD": "#V1929959",
            "LEX": "GAMES",
            "WNSENSE": "game%1:04:00::"
          },
          "start": 19,
          "end": 35
        },
        "V1929959": {
          "id": "V1929959",
          "indicator": "F",
          "type": "STATE-RESULTING-FROM",
          "word": null,
          "roles": {
            "FIGURE": "#V1929934",
            "GROUND": "#V1929929",
            "DEGREE": "#V1929921",
            "LEX": "LOVED"
          },
          "start": 19,
          "end": 30
        },
        "V1929929": {
          "id": "V1929929",
          "indicator": "F",
          "type": "APPRECIATE",
          "word": "LOVE",
          "roles": {
            "NEUTRAL": "#V1929934",
            "WNSENSE": "love%2:37:00::"
          },
          "start": 19,
          "end": 30
        },
        "V1929921": {
          "id": "V1929921",
          "indicator": "F",
          "type": "DEGREE-MODIFIER-HIGH",
          "word": "THAT",
          "roles": {
            "FIGURE": "#V1929959",
            "LEX": "THAT",
            "WNSENSE": "profusely%4:02:00"
          },
          "start": 19,
          "end": 24
        },
        "root": "#V1930521"
      }
    ],
    [
      {
        "V1930806": {
          "id": "V1930806",
          "indicator": "SPEECHACT",
          "type": "SA_TELL",
          "word": null,
          "roles": {
            "CONTENT": "#V1929860",
            "LEX": "WERE"
          },
          "start": 0,
          "end": 35
        },
        "V1929860": {
          "id": "V1929860",
          "indicator": "F",
          "type": "BE",
          "word": "BE",
          "roles": {
            "NEUTRAL": "#V1929852",
            "NEUTRAL1": "#V1929934",
            "BENEFICIARY": "#V1929912",
            "TENSE": "PAST",
            "LEX": "WERE",
            "WNSENSE": "be%2:42:06::"
          },
          "start": 0,
          "end": 35
        },
        "V1929852": {
          "id": "V1929852",
          "indicator": "PRO-SET",
          "type": "REFERENTIAL-SEM",
          "word": "THEY",
          "roles": {
            "PROFORM": "THEY",
            "LEX": "THEY",
            "WNSENSE": "entity%1:03:00"
          },
          "start": 0,
          "end": 5
        },
        "V1929912": {
          "id": "V1929912",
          "indicator": "A",
          "type": "FAMILY-GROUP",
          "word": "FAMILY",
          "roles": {
            "MOD": "#V1929929",
            "LEX": "FAMILY",
            "WNSENSE": "family%1:14:02::"
          },
          "start": 10,
          "end": 30
        },
        "V1929929": {
          "id": "V1929929",
          "indicator": "F",
          "type": "APPRECIATE",
          "word": "LOVE",
          "roles": {
            "EXPERIENCER": "#V1929920",
            "NEUTRAL": "#V1929912",
            "TENSE": "PAST",
            "LEX": "LOVED",
            "WNSENSE": "love%2:37:00::"
          },
          "start": 19,
          "end": 30
        },
        "V1929920": {
          "id": "V1929920",
          "indicator": "PRO",
          "type": "REFERENTIAL-SEM",
          "word": "THAT",
          "roles": {
            "PROFORM": "THAT",
            "LEX": "THAT",
            "WNSENSE": "entity%1:03:00"
          },
          "start": 19,
          "end": 24
        },
        "V1929934": {
          "id": "V1929934",
          "indicator": "INDEF-SET",
          "type": "GAME",
          "word": "GAME",
          "roles": {
            "LEX": "GAMES",
            "WNSENSE": "game%1:04:00::"
          },
          "start": 30,
          "end": 35
        },
        "root": "#V1930806"
      }
    ],
    [
      {
        "V1930561": {
          "id": "V1930561",
          "indicator": "SPEECHACT",
          "type": "SA_TELL",
          "word": null,
          "roles": {
            "CONTENT": "#V1929860",
            "LEX": "WERE"
          },
          "start": 0,
          "end": 35
        },
        "V1929860": {
          "id": "V1929860",
          "indicator": "F",
          "type": "BE",
          "word": "BE",
          "roles": {
            "NEUTRAL": "#V1929852",
            "NEUTRAL1": "#V1929934",
            "AFFECTED-RESULT": "#V1930411",
            "TENSE": "PAST",
            "LEX": "WERE",
            "WNSENSE": "be%2:42:06::"
          },
          "start": 0,
          "end": 35
        },
        "V1930411": {
          "id": "V1930411",
          "indicator": "F",
          "type": "RECIPIENT",
          "word": "IOBJ",
          "roles": {
            "GROUND": "#V1929912",
            "FIGURE": "#V1929860"
          },
          "start": 0,
          "end": 35
        },
        "V1929852": {
          "id": "V1929852",
          "indicator": "PRO-SET",
          "type": "REFERENTIAL-SEM",
          "word": "THEY",
          "roles": {
            "PROFORM": "THEY",
            "LEX": "THEY",
            "WNSENSE": "entity%1:03:00"
          },
          "start": 0,
          "end": 5
        },
        "V1929912": {
          "id": "V1929912",
          "indicator": "A",
          "type": "FAMILY-GROUP",
          "word": "FAMILY",
          "roles": {
            "LEX": "FAMILY",
            "WNSENSE": "family%1:14:02::"
          },
          "start": 10,
          "end": 19
        },
        "V1929934": {
          "id": "V1929934",
          "indicator": "INDEF-SET",
          "type": "GAME",
          "word": "GAME",
          "roles": {
            "MOD": "#V1929959",
            "LEX": "GAMES",
            "WNSENSE": "game%1:04:00::"
          },
          "start": 19,
          "end": 35
        },
        "V1929959": {
          "id": "V1929959",
          "indicator": "F",
          "type": "STATE-RESULTING-FROM",
          "word": null,
          "roles": {
            "FIGURE": "#V1929934",
            "GROUND": "#V1929929",
            "DEGREE": "#V1929921",
            "LEX": "LOVED"
          },
          "start": 19,
          "end": 30
        },
        "V1929929": {
          "id": "V1929929",
          "indicator": "F",
          "type": "APPRECIATE",
          "word": "LOVE",
          "roles": {
            "NEUTRAL": "#V1929934",
            "WNSENSE": "love%2:37:00::"
          },
          "start": 19,
          "end": 30
        },
        "V1929921": {
          "id": "V1929921",
          "indicator": "F",
          "type": "DEGREE-MODIFIER-HIGH",
          "word": "THAT",
          "roles": {
            "FIGURE": "#V1929959",
            "LEX": "THAT",
            "WNSENSE": "profusely%4:02:00"
          },
          "start": 19,
          "end": 24
        },
        "root": "#V1930561"
      }
    ],
    [
      {
        "V1930835": {
          "id": "V1930835",
          "indicator": "SPEECHACT",
          "type": "SA_TELL",
          "word": null,
          "roles": {
            "CONTENT": "#V1929860",
            "LEX": "WERE"
          },
          "start": 0,
          "end": 35
        },
        "V1929860": {
          "id": "V1929860",
          "indicator": "F",
          "type": "BE",
          "word": "BE",
          "roles": {
            "NEUTRAL": "#V1929852",
            "NEUTRAL1": "#V1929934",
            "AFFECTED-RESULT": "#V1930411",
            "TENSE": "PAST",
            "LEX": "WERE",
            "WNSENSE": "be%2:42:06::"
          },
          "start": 0,
          "end": 35
        },
        "V1930411": {
          "id": "V1930411",
          "indicator": "F",
          "type": "RECIPIENT",
          "word": "IOBJ",
          "roles": {
            "GROUND": "#V1929912",
            "FIGURE": "#V1929860"
          },
          "start": 0,
          "end": 35
        },
        "V1929852": {
          "id": "V1929852",
          "indicator": "PRO-SET",
          "type": "REFERENTIAL-SEM",
          "word": "THEY",
          "roles": {
            "PROFORM": "THEY",
            "LEX": "THEY",
            "WNSENSE": "entity%1:03:00"
          },
          "start": 0,
          "end": 5
        },
        "V1929912": {
          "id": "V1929912",
          "indicator": "A",
          "type": "FAMILY-GROUP",
          "word": "FAMILY",
          "roles": {
            "MOD": "#V1929929",
            "LEX": "FAMILY",
            "WNSENSE": "family%1:14:02::"
          },
          "start": 10,
          "end": 30
        },
        "V1929929": {
          "id": "V1929929",
          "indicator": "F",
          "type": "APPRECIATE",
          "word": "LOVE",
          "roles": {
            "EXPERIENCER": "#V1929920",
            "NEUTRAL": "#V1929912",
            "TENSE": "PAST",
            "LEX": "LOVED",
            "WNSENSE": "love%2:37:00::"
          },
          "start": 19,
          "end": 30
        },
        "V1929920": {
          "id": "V1929920",
          "indicator": "PRO",
          "type": "REFERENTIAL-SEM",
          "word": "THAT",
          "roles": {
            "PROFORM": "THAT",
            "LEX": "THAT",
            "WNSENSE": "entity%1:03:00"
          },
          "start": 19,
          "end": 24
        },
        "V1929934": {
          "id": "V1929934",
          "indicator": "INDEF-SET",
          "type": "GAME",
          "word": "GAME",
          "roles": {
            "LEX": "GAMES",
            "WNSENSE": "game%1:04:00::"
          },
          "start": 30,
          "end": 35
        },
        "root": "#V1930835"
      }
    ],
    [
      {
        "V1930729": {
          "id": "V1930729",
          "indicator": "SPEECHACT",
          "type": "SA_TELL",
          "word": null,
          "roles": {
            "CONTENT": "#V1929859",
            "LEX": "WERE"
          },
          "start": 0,
          "end": 35
        },
        "V1929859": {
          "id": "V1929859",
          "indicator": "F",
          "type": "HAVE-PROPERTY",
          "word": "BE",
          "roles": {
            "NEUTRAL": "#V1929852",
            "FORMAL": "#V1930234",
            "TENSE": "PAST",
            "LEX": "WERE",
            "WNSENSE": "be%2:42:03::"
          },
          "start": 0,
          "end": 35
        },
        "V1929852": {
          "id": "V1929852",
          "indicator": "PRO-SET",
          "type": "REFERENTIAL-SEM",
          "word": "THEY",
          "roles": {
            "PROFORM": "THEY",
            "LEX": "THEY",
            "WNSENSE": "entity%1:03:00"
          },
          "start": 0,
          "end": 5
        },
        "V1930234": {
          "id": "V1930234",
          "indicator": "F",
          "type": "MEMBERSHIP",
          "word": null,
          "roles": {
            "FIGURE": "#V1929852",
            "GROUND": "#V1929912",
            "LEX": "FAMILY"
          },
          "start": 10,
          "end": 35
        },
        "V1929912": {
          "id": "V1929912",
          "indicator": "BARE",
          "type": "FAMILY-GROUP",
          "word": "FAMILY",
          "roles": {
            "ASSOC-WITH": "#V1929887",
            "MOD": "#V1929929"
          },
          "start": 10,
          "end": 35
        },
        "V1929887": {
          "id": "V1929887",
          "indicator": "THE",
          "type": "LETTER-SYMBOL",
          "word": null,
          "roles": {
            "NAME-OF": "A",
            "LEX": "A",
            "WNSENSE": "a%1:10:00::"
          },
          "start": 10,
          "end": 12
        },
        "V1929929": {
          "id": "V1929929",
          "indicator": "F",
          "type": "APPRECIATE",
          "word": "LOVE",
          "roles": {
            "EXPERIENCER": "#V1929912",
            "NEUTRAL": "#V1929934",
            "TENSE": "PAST",
            "LEX": "LOVED",
            "WNSENSE": "love%2:37:00::"
          },
          "start": 19,
          "end": 35
        },
        "V1929934": {
          "id": "V1929934",
          "indicator": "INDEF-SET",
          "type": "GAME",
          "word": "GAME",
          "roles": {
            "LEX": "GAMES",
            "WNSENSE": "game%1:04:00::"
          },
          "start": 30,
          "end": 35
        },
        "root": "#V1930729"
      }
    ],
    [
      {
        "V1930744": {
          "id": "V1930744",
          "indicator": "SPEECHACT",
          "type": "SA_TELL",
          "word": null,
          "roles": {
            "CONTENT": "#V1929859",
            "LEX": "WERE"
          },
          "start": 0,
          "end": 35
        },
        "V1929859": {
          "id": "V1929859",
          "indicator": "F",
          "type": "HAVE-PROPERTY",
          "word": "BE",
          "roles": {
            "NEUTRAL": "#V1929852",
            "FORMAL": "#V1930257",
            "TENSE": "PAST",
            "LEX": "WERE",
            "WNSENSE": "be%2:42:03::"
          },
          "start": 0,
          "end": 35
        },
        "V1929852": {
          "id": "V1929852",
          "indicator": "PRO-SET",
          "type": "REFERENTIAL-SEM",
          "word": "THEY",
          "roles": {
            "PROFORM": "THEY",
            "LEX": "THEY",
            "WNSENSE": "entity%1:03:00"
          },
          "start": 0,
          "end": 5
        },
        "V1930257": {
          "id": "V1930257",
          "indicator": "F",
          "type": "MEMBERSHIP",
          "word": null,
          "roles": {
            "FIGURE": "#V1929852",
            "GROUND": "#V1929912",
            "LEX": "FAMILY"
          },
          "start": 10,
          "end": 35
        },
        "V1929912": {
          "id": "V1929912",
          "indicator": "BARE",
          "type": "FAMILY-GROUP",
          "word": "FAMILY",
          "roles": {
            "ASSOC-WITH": "#V1930155",
            "MOD": "#V1929929"
          },
          "start": 10,
          "end": 35
        },
        "V1930155": {
          "id": "V1930155",
          "indicator": "THE",
          "type": "TIME-LOC",
          "word": null,
          "roles": {
            "DAY-OF-WEEK": "#V1930136",
            "LEX": "A"
          },
          "start": 10,
          "end": 12
        },
        "V1930136": {
          "id": "V1930136",
          "indicator": "THE",
          "type": "SEQUENCE",
          "word": null,
          "roles": {
            "NAME-OF": "(A)",
            "VAL": "(A)",
            "LEX": "A"
          },
          "start": 10,
          "end": 12
        },
        "V1929929": {
          "id": "V1929929",
          "indicator": "F",
          "type": "APPRECIATE",
          "word": "LOVE",
          "roles": {
            "EXPERIENCER": "#V1929912",
            "NEUTRAL": "#V1929934",
            "TENSE": "PAST",
            "LEX": "LOVED",
            "WNSENSE": "love%2:37:00::"
          },
          "start": 19,
          "end": 35
        },
        "V1929934": {
          "id": "V1929934",
          "indicator": "INDEF-SET",
          "type": "GAME",
          "word": "GAME",
          "roles": {
            "LEX": "GAMES",
            "WNSENSE": "game%1:04:00::"
          },
          "start": 30,
          "end": 35
        },
        "root": "#V1930744"
      }
    ],
    [
      {
        "V1930967": {
          "id": "V1930967",
          "indicator": "SPEECHACT",
          "type": "SA_TELL",
          "word": null,
          "roles": {
            "CONTENT": "#V1929860",
            "LEX": "WERE"
          },
          "start": 0,
          "end": 35
        },
        "V1929860": {
          "id": "V1929860",
          "indicator": "F",
          "type": "BE",
          "word": "BE",
          "roles": {
            "NEUTRAL": "#V1929852",
            "NEUTRAL1": "#V1929934",
            "BENEFICIARY": "#V1929912",
            "TENSE": "PAST",
            "LEX": "WERE",
            "WNSENSE": "be%2:42:06::"
          },
          "start": 0,
          "end": 35
        },
        "V1929852": {
          "id": "V1929852",
          "indicator": "PRO-SET",
          "type": "REFERENTIAL-SEM",
          "word": "THEY",
          "roles": {
            "PROFORM": "THEY",
            "LEX": "THEY",
            "WNSENSE": "entity%1:03:00"
          },
          "start": 0,
          "end": 5
        },
        "V1929912": {
          "id": "V1929912",
          "indicator": "BARE",
          "type": "FAMILY-GROUP",
          "word": "FAMILY",
          "roles": {
            "ASSOC-WITH": "#V1929887",
            "LEX": "FAMILY",
            "WNSENSE": "family%1:14:02::"
          },
          "start": 10,
          "end": 19
        },
        "V1929887": {
          "id": "V1929887",
          "indicator": "THE",
          "type": "LETTER-SYMBOL",
          "word": null,
          "roles": {
            "NAME-OF": "A",
            "LEX": "A",
            "WNSENSE": "a%1:10:00::"
          },
          "start": 10,
          "end": 12
        },
        "V1929934": {
          "id": "V1929934",
          "indicator": "INDEF-SET",
          "type": "GAME",
          "word": "GAME",
          "roles": {
            "MOD": "#V1929959",
            "LEX": "GAMES",
            "WNSENSE": "game%1:04:00::"
          },
          "start": 19,
          "end": 35
        },
        "V1929959": {
          "id": "V1929959",
          "indicator": "F",
          "type": "STATE-RESULTING-FROM",
          "word": null,
          "roles": {
            "FIGURE": "#V1929934",
            "GROUND": "#V1929929",
            "DEGREE": "#V1929921",
            "LEX": "LOVED"
          },
          "start": 19,
          "end": 30
        },
        "V1929929": {
          "id": "V1929929",
          "indicator": "F",
          "type": "APPRECIATE",
          "word": "LOVE",
          "roles": {
            "NEUTRAL": "#V1929934",
            "WNSENSE": "love%2:37:00::"
          },
          "start": 19,
          "end": 30
        },
        "V1929921": {
          "id": "V1929921",
          "indicator": "F",
          "type": "DEGREE-MODIFIER-HIGH",
          "word": "THAT",
          "roles": {
            "FIGURE": "#V1929959",
            "LEX": "THAT",
            "WNSENSE": "profusely%4:02:00"
          },
          "start": 19,
          "end": 24
        },
        "root": "#V1930967"
      }
    ],
    [
      {
        "V1931045": {
          "id": "V1931045",
          "indicator": "SPEECHACT",
          "type": "SA_TELL",
          "word": null,
          "roles": {
            "CONTENT": "#V1929860",
            "LEX": "WERE"
          },
          "start": 0,
          "end": 35
        },
        "V1929860": {
          "id": "V1929860",
          "indicator": "F",
          "type": "BE",
          "word": "BE",
          "roles": {
            "NEUTRAL": "#V1929852",
            "NEUTRAL1": "#V1929934",
            "BENEFICIARY": "#V1929912",
            "TENSE": "PAST",
            "LEX": "WERE",
            "WNSENSE": "be%2:42:06::"
          },
          "start": 0,
          "end": 35
        },
        "V1929852": {
          "id": "V1929852",
          "indicator": "PRO-SET",
          "type": "REFERENTIAL-SEM",
          "word": "THEY",
          "roles": {
            "PROFORM": "THEY",
            "LEX": "THEY",
            "WNSENSE": "entity%1:03:00"
          },
          "start": 0,
          "end": 5
        },
        "V1929912": {
          "id": "V1929912",
          "indicator": "BARE",
          "type": "FAMILY-GROUP",
          "word": "FAMILY",
          "roles": {
            "ASSOC-WITH": "#V1930155",
            "LEX": "FAMILY",
            "WNSENSE": "family%1:14:02::"
          },
          "start": 10,
          "end": 19
        },
        "V1930155": {
          "id": "V1930155",
          "indicator": "THE",
          "type": "TIME-LOC",
          "word": null,
          "roles": {
            "DAY-OF-WEEK": "#V1930136",
            "LEX": "A"
          },
          "start": 10,
          "end": 12
        },
        "V1930136": {
          "id": "V1930136",
          "indicator": "THE",
          "type": "SEQUENCE",
          "word": null,
          "roles": {
            "NAME-OF": "(A)",
            "VAL": "(A)",
            "LEX": "A"
          },
          "start": 10,
          "end": 12
        },
        "V1929934": {
          "id": "V1929934",
          "indicator": "INDEF-SET",
          "type": "GAME",
          "word": "GAME",
          "roles": {
            "MOD": "#V1929959",
            "LEX": "GAMES",
            "WNSENSE": "game%1:04:00::"
          },
          "start": 19,
          "end": 35
        },
        "V1929959": {
          "id": "V1929959",
          "indicator": "F",
          "type": "STATE-RESULTING-FROM",
          "word": null,
          "roles": {
            "FIGURE": "#V1929934",
            "GROUND": "#V1929929",
            "DEGREE": "#V1929921",
            "LEX": "LOVED"
          },
          "start": 19,
          "end": 30
        },
        "V1929929": {
          "id": "V1929929",
          "indicator": "F",
          "type": "APPRECIATE",
          "word": "LOVE",
          "roles": {
            "NEUTRAL": "#V1929934",
            "WNSENSE": "love%2:37:00::"
          },
          "start": 19,
          "end": 30
        },
        "V1929921": {
          "id": "V1929921",
          "indicator": "F",
          "type": "DEGREE-MODIFIER-HIGH",
          "word": "THAT",
          "roles": {
            "FIGURE": "#V1929959",
            "LEX": "THAT",
            "WNSENSE": "profusely%4:02:00"
          },
          "start": 19,
          "end": 24
        },
        "root": "#V1931045"
      }
    ],
    [
      {
        "V1931103": {
          "id": "V1931103",
          "indicator": "SPEECHACT",
          "type": "SA_TELL",
          "word": null,
          "roles": {
            "CONTENT": "#V1929860",
            "LEX": "WERE"
          },
          "start": 0,
          "end": 35
        },
        "V1929860": {
          "id": "V1929860",
          "indicator": "F",
          "type": "BE",
          "word": "BE",
          "roles": {
            "NEUTRAL": "#V1929852",
            "NEUTRAL1": "#V1929934",
            "AFFECTED-RESULT": "#V1930411",
            "TENSE": "PAST",
            "LEX": "WERE",
            "WNSENSE": "be%2:42:06::"
          },
          "start": 0,
          "end": 35
        },
        "V1930411": {
          "id": "V1930411",
          "indicator": "F",
          "type": "RECIPIENT",
          "word": "IOBJ",
          "roles": {
            "GROUND": "#V1929912",
            "FIGURE": "#V1929860"
          },
          "start": 0,
          "end": 35
        },
        "V1929852": {
          "id": "V1929852",
          "indicator": "PRO-SET",
          "type": "REFERENTIAL-SEM",
          "word": "THEY",
          "roles": {
            "PROFORM": "THEY",
            "LEX": "THEY",
            "WNSENSE": "entity%1:03:00"
          },
          "start": 0,
          "end": 5
        },
        "V1929912": {
          "id": "V1929912",
          "indicator": "BARE",
          "type": "FAMILY-GROUP",
          "word": "FAMILY",
          "roles": {
            "ASSOC-WITH": "#V1929887",
            "LEX": "FAMILY",
            "WNSENSE": "family%1:14:02::"
          },
          "start": 10,
          "end": 19
        },
        "V1929887": {
          "id": "V1929887",
          "indicator": "THE",
          "type": "LETTER-SYMBOL",
          "word": null,
          "roles": {
            "NAME-OF": "A",
            "LEX": "A",
            "WNSENSE": "a%1:10:00::"
          },
          "start": 10,
          "end": 12
        },
        "V1929934": {
          "id": "V1929934",
          "indicator": "INDEF-SET",
          "type": "GAME",
          "word": "GAME",
          "roles": {
            "MOD": "#V1929959",
            "LEX": "GAMES",
            "WNSENSE": "game%1:04:00::"
          },
          "start": 19,
          "end": 35
        },
        "V1929959": {
          "id": "V1929959",
          "indicator": "F",
          "type": "STATE-RESULTING-FROM",
          "word": null,
          "roles": {
            "FIGURE": "#V1929934",
            "GROUND": "#V1929929",
            "DEGREE": "#V1929921",
            "LEX": "LOVED"
          },
          "start": 19,
          "end": 30
        },
        "V1929929": {
          "id": "V1929929",
          "indicator": "F",
          "type": "APPRECIATE",
          "word": "LOVE",
          "roles": {
            "NEUTRAL": "#V1929934",
            "WNSENSE": "love%2:37:00::"
          },
          "start": 19,
          "end": 30
        },
        "V1929921": {
          "id": "V1929921",
          "indicator": "F",
          "type": "DEGREE-MODIFIER-HIGH",
          "word": "THAT",
          "roles": {
            "FIGURE": "#V1929959",
            "LEX": "THAT",
            "WNSENSE": "profusely%4:02:00"
          },
          "start": 19,
          "end": 24
        },
        "root": "#V1931103"
      }
    ],
    [
      {
        "V1931156": {
          "id": "V1931156",
          "indicator": "SPEECHACT",
          "type": "SA_TELL",
          "word": null,
          "roles": {
            "CONTENT": "#V1929860",
            "LEX": "WERE"
          },
          "start": 0,
          "end": 35
        },
        "V1929860": {
          "id": "V1929860",
          "indicator": "F",
          "type": "BE",
          "word": "BE",
          "roles": {
            "NEUTRAL": "#V1929852",
            "NEUTRAL1": "#V1929934",
            "AFFECTED-RESULT": "#V1930411",
            "TENSE": "PAST",
            "LEX": "WERE",
            "WNSENSE": "be%2:42:06::"
          },
          "start": 0,
          "end": 35
        },
        "V1930411": {
          "id": "V1930411",
          "indicator": "F",
          "type": "RECIPIENT",
          "word": "IOBJ",
          "roles": {
            "GROUND": "#V1929912",
            "FIGURE": "#V1929860"
          },
          "start": 0,
          "end": 35
        },
        "V1929852": {
          "id": "V1929852",
          "indicator": "PRO-SET",
          "type": "REFERENTIAL-SEM",
          "word": "THEY",
          "roles": {
            "PROFORM": "THEY",
            "LEX": "THEY",
            "WNSENSE": "entity%1:03:00"
          },
          "start": 0,
          "end": 5
        },
        "V1929912": {
          "id": "V1929912",
          "indicator": "BARE",
          "type": "FAMILY-GROUP",
          "word": "FAMILY",
          "roles": {
            "ASSOC-WITH": "#V1930155",
            "LEX": "FAMILY",
            "WNSENSE": "family%1:14:02::"
          },
          "start": 10,
          "end": 19
        },
        "V1930155": {
          "id": "V1930155",
          "indicator": "THE",
          "type": "TIME-LOC",
          "word": null,
          "roles": {
            "DAY-OF-WEEK": "#V1930136",
            "LEX": "A"
          },
          "start": 10,
          "end": 12
        },
        "V1930136": {
          "id": "V1930136",
          "indicator": "THE",
          "type": "SEQUENCE",
          "word": null,
          "roles": {
            "NAME-OF": "(A)",
            "VAL": "(A)",
            "LEX": "A"
          },
          "start": 10,
          "end": 12
        },
        "V1929934": {
          "id": "V1929934",
          "indicator": "INDEF-SET",
          "type": "GAME",
          "word": "GAME",
          "roles": {
            "MOD": "#V1929959",
            "LEX": "GAMES",
            "WNSENSE": "game%1:04:00::"
          },
          "start": 19,
          "end": 35
        },
        "V1929959": {
          "id": "V1929959",
          "indicator": "F",
          "type": "STATE-RESULTING-FROM",
          "word": null,
          "roles": {
            "FIGURE": "#V1929934",
            "GROUND": "#V1929929",
            "DEGREE": "#V1929921",
            "LEX": "LOVED"
          },
          "start": 19,
          "end": 30
        },
        "V1929929": {
          "id": "V1929929",
          "indicator": "F",
          "type": "APPRECIATE",
          "word": "LOVE",
          "roles": {
            "NEUTRAL": "#V1929934",
            "WNSENSE": "love%2:37:00::"
          },
          "start": 19,
          "end": 30
        },
        "V1929921": {
          "id": "V1929921",
          "indicator": "F",
          "type": "DEGREE-MODIFIER-HIGH",
          "word": "THAT",
          "roles": {
            "FIGURE": "#V1929959",
            "LEX": "THAT",
            "WNSENSE": "profusely%4:02:00"
          },
          "start": 19,
          "end": 24
        },
        "root": "#V1931156"
      }
    ],
    [
      {
        "V1931248": {
          "id": "V1931248",
          "indicator": "SPEECHACT",
          "type": "SA_TELL",
          "word": null,
          "roles": {
            "CONTENT": "#V1929860",
            "LEX": "WERE"
          },
          "start": 0,
          "end": 35
        },
        "V1929860": {
          "id": "V1929860",
          "indicator": "F",
          "type": "BE",
          "word": "BE",
          "roles": {
            "NEUTRAL": "#V1929852",
            "NEUTRAL1": "#V1929934",
            "BENEFICIARY": "#V1929912",
            "TENSE": "PAST",
            "LEX": "WERE",
            "WNSENSE": "be%2:42:06::"
          },
          "start": 0,
          "end": 35
        },
        "V1929852": {
          "id": "V1929852",
          "indicator": "PRO-SET",
          "type": "REFERENTIAL-SEM",
          "word": "THEY",
          "roles": {
            "PROFORM": "THEY",
            "LEX": "THEY",
            "WNSENSE": "entity%1:03:00"
          },
          "start": 0,
          "end": 5
        },
        "V1929912": {
          "id": "V1929912",
          "indicator": "BARE",
          "type": "FAMILY-GROUP",
          "word": "FAMILY",
          "roles": {
            "ASSOC-WITH": "#V1929887",
            "MOD": "#V1929929",
            "LEX": "FAMILY",
            "WNSENSE": "family%1:14:02::"
          },
          "start": 10,
          "end": 30
        },
        "V1929887": {
          "id": "V1929887",
          "indicator": "THE",
          "type": "LETTER-SYMBOL",
          "word": null,
          "roles": {
            "NAME-OF": "A",
            "LEX": "A",
            "WNSENSE": "a%1:10:00::"
          },
          "start": 10,
          "end": 12
        },
        "V1929929": {
          "id": "V1929929",
          "indicator": "F",
          "type": "APPRECIATE",
          "word": "LOVE",
          "roles": {
            "EXPERIENCER": "#V1929920",
            "NEUTRAL": "#V1929912",
            "TENSE": "PAST",
            "LEX": "LOVED",
            "WNSENSE": "love%2:37:00::"
          },
          "start": 19,
          "end": 30
        },
        "V1929920": {
          "id": "V1929920",
          "indicator": "PRO",
          "type": "REFERENTIAL-SEM",
          "word": "THAT",
          "roles": {
            "PROFORM": "THAT",
            "LEX": "THAT",
            "WNSENSE": "entity%1:03:00"
          },
          "start": 19,
          "end": 24
        },
        "V1929934": {
          "id": "V1929934",
          "indicator": "INDEF-SET",
          "type": "GAME",
          "word": "GAME",
          "roles": {
            "LEX": "GAMES",
            "WNSENSE": "game%1:04:00::"
          },
          "start": 30,
          "end": 35
        },
        "root": "#V1931248"
      }
    ],
    [
      {
        "V1931285": {
          "id": "V1931285",
          "indicator": "SPEECHACT",
          "type": "SA_TELL",
          "word": null,
          "roles": {
            "CONTENT": "#V1929860",
            "LEX": "WERE"
          },
          "start": 0,
          "end": 35
        },
        "V1929860": {
          "id": "V1929860",
          "indicator": "F",
          "type": "BE",
          "word": "BE",
          "roles": {
            "NEUTRAL": "#V1929852",
            "NEUTRAL1": "#V1929934",
            "BENEFICIARY": "#V1929912",
            "TENSE": "PAST",
            "LEX": "WERE",
            "WNSENSE": "be%2:42:06::"
          },
          "start": 0,
          "end": 35
        },
        "V1929852": {
          "id": "V1929852",
          "indicator": "PRO-SET",
          "type": "REFERENTIAL-SEM",
          "word": "THEY",
          "roles": {
            "PROFORM": "THEY",
            "LEX": "THEY",
            "WNSENSE": "entity%1:03:00"
          },
          "start": 0,
          "end": 5
        },
        "V1929912": {
          "id": "V1929912",
          "indicator": "BARE",
          "type": "FAMILY-GROUP",
          "word": "FAMILY",
          "roles": {
            "ASSOC-WITH": "#V1930155",
            "MOD": "#V1929929",
            "LEX": "FAMILY",
            "WNSENSE": "family%1:14:02::"
          },
          "start": 10,
          "end": 30
        },
        "V1930155": {
          "id": "V1930155",
          "indicator": "THE",
          "type": "TIME-LOC",
          "word": null,
          "roles": {
            "DAY-OF-WEEK": "#V1930136",
            "LEX": "A"
          },
          "start": 10,
          "end": 12
        },
        "V1930136": {
          "id": "V1930136",
          "indicator": "THE",
          "type": "SEQUENCE",
          "word": null,
          "roles": {
            "NAME-OF": "(A)",
            "VAL": "(A)",
            "LEX": "A"
          },
          "start": 10,
          "end": 12
        },
        "V1929929": {
          "id": "V1929929",
          "indicator": "F",
          "type": "APPRECIATE",
          "word": "LOVE",
          "roles": {
            "EXPERIENCER": "#V1929920",
            "NEUTRAL": "#V1929912",
            "TENSE": "PAST",
            "LEX": "LOVED",
            "WNSENSE": "love%2:37:00::"
          },
          "start": 19,
          "end": 30
        },
        "V1929920": {
          "id": "V1929920",
          "indicator": "PRO",
          "type": "REFERENTIAL-SEM",
          "word": "THAT",
          "roles": {
            "PROFORM": "THAT",
            "LEX": "THAT",
            "WNSENSE": "entity%1:03:00"
          },
          "start": 19,
          "end": 24
        },
        "V1929934": {
          "id": "V1929934",
          "indicator": "INDEF-SET",
          "type": "GAME",
          "word": "GAME",
          "roles": {
            "LEX": "GAMES",
            "WNSENSE": "game%1:04:00::"
          },
          "start": 30,
          "end": 35
        },
        "root": "#V1931285"
      }
    ],
    [
      {
        "V1931314": {
          "id": "V1931314",
          "indicator": "SPEECHACT",
          "type": "SA_TELL",
          "word": null,
          "roles": {
            "CONTENT": "#V1929860",
            "LEX": "WERE"
          },
          "start": 0,
          "end": 35
        },
        "V1929860": {
          "id": "V1929860",
          "indicator": "F",
          "type": "BE",
          "word": "BE",
          "roles": {
            "NEUTRAL": "#V1929852",
            "NEUTRAL1": "#V1929934",
            "AFFECTED-RESULT": "#V1930411",
            "TENSE": "PAST",
            "LEX": "WERE",
            "WNSENSE": "be%2:42:06::"
          },
          "start": 0,
          "end": 35
        },
        "V1930411": {
          "id": "V1930411",
          "indicator": "F",
          "type": "RECIPIENT",
          "word": "IOBJ",
          "roles": {
            "GROUND": "#V1929912",
            "FIGURE": "#V1929860"
          },
          "start": 0,
          "end": 35
        },
        "V1929852": {
          "id": "V1929852",
          "indicator": "PRO-SET",
          "type": "REFERENTIAL-SEM",
          "word": "THEY",
          "roles": {
            "PROFORM": "THEY",
            "LEX": "THEY",
            "WNSENSE": "entity%1:03:00"
          },
          "start": 0,
          "end": 5
        },
        "V1929912": {
          "id": "V1929912",
          "indicator": "BARE",
          "type": "FAMILY-GROUP",
          "word": "FAMILY",
          "roles": {
            "ASSOC-WITH": "#V1929887",
            "MOD": "#V1929929",
            "LEX": "FAMILY",
            "WNSENSE": "family%1:14:02::"
          },
          "start": 10,
          "end": 30
        },
        "V1929887": {
          "id": "V1929887",
          "indicator": "THE",
          "type": "LETTER-SYMBOL",
          "word": null,
          "roles": {
            "NAME-OF": "A",
            "LEX": "A",
            "WNSENSE": "a%1:10:00::"
          },
          "start": 10,
          "end": 12
        },
        "V1929929": {
          "id": "V1929929",
          "indicator": "F",
          "type": "APPRECIATE",
          "word": "LOVE",
          "roles": {
            "EXPERIENCER": "#V1929920",
            "NEUTRAL": "#V1929912",
            "TENSE": "PAST",
            "LEX": "LOVED",
            "WNSENSE": "love%2:37:00::"
          },
          "start": 19,
          "end": 30
        },
        "V1929920": {
          "id": "V1929920",
          "indicator": "PRO",
          "type": "REFERENTIAL-SEM",
          "word": "THAT",
          "roles": {
            "PROFORM": "THAT",
            "LEX": "THAT",
            "WNSENSE": "entity%1:03:00"
          },
          "start": 19,
          "end": 24
        },
        "V1929934": {
          "id": "V1929934",
          "indicator": "INDEF-SET",
          "type": "GAME",
          "word": "GAME",
          "roles": {
            "LEX": "GAMES",
            "WNSENSE": "game%1:04:00::"
          },
          "start": 30,
          "end": 35
        },
        "root": "#V1931314"
      }
    ],
    [
      {
        "V1930940": {
          "id": "V1930940",
          "indicator": "SPEECHACT",
          "type": "SA_TELL",
          "word": null,
          "roles": {
            "CONTENT": "#V1929860",
            "LEX": "WERE"
          },
          "start": 0,
          "end": 35
        },
        "V1929860": {
          "id": "V1929860",
          "indicator": "F",
          "type": "BE",
          "word": "BE",
          "roles": {
            "NEUTRAL": "#V1929852",
            "NEUTRAL1": "#V1929934",
            "BENEFICIARY": "#V1929912",
            "TENSE": "PAST",
            "LEX": "WERE",
            "WNSENSE": "be%2:42:06::"
          },
          "start": 0,
          "end": 35
        },
        "V1929852": {
          "id": "V1929852",
          "indicator": "PRO-SET",
          "type": "REFERENTIAL-SEM",
          "word": "THEY",
          "roles": {
            "PROFORM": "THEY",
            "LEX": "THEY",
            "WNSENSE": "entity%1:03:00"
          },
          "start": 0,
          "end": 5
        },
        "V1929912": {
          "id": "V1929912",
          "indicator": "A",
          "type": "FAMILY-GROUP",
          "word": "FAMILY",
          "roles": {
            "LEX": "FAMILY",
            "WNSENSE": "family%1:14:02::"
          },
          "start": 10,
          "end": 19
        },
        "V1929934": {
          "id": "V1929934",
          "indicator": "INDEF-SET",
          "type": "GAME",
          "word": "GAME",
          "roles": {
            "MOD": "#V1929959",
            "LEX": "GAMES",
            "WNSENSE": "game%1:04:00::"
          },
          "start": 19,
          "end": 35
        },
        "V1929959": {
          "id": "V1929959",
          "indicator": "F",
          "type": "STATE-RESULTING-FROM",
          "word": null,
          "roles": {
            "FIGURE": "#V1929934",
            "GROUND": "#V1929929",
            "DEGREE": "#V1929921",
            "LEX": "LOVED"
          },
          "start": 19,
          "end": 30
        },
        "V1929929": {
          "id": "V1929929",
          "indicator": "F",
          "type": "APPRECIATE",
          "word": "LOVE",
          "roles": {
            "NEUTRAL": "#V1929934",
            "WNSENSE": "love%2:37:00::"
          },
          "start": 19,
          "end": 30
        },
        "V1929921": {
          "id": "V1929921",
          "indicator": "F",
          "type": "DEGREE-MODIFIER-HIGH",
          "word": "THAT",
          "roles": {
            "FIGURE": "#V1929959",
            "LEX": "THAT",
            "WNSENSE": "profusely%4:02:00"
          },
          "start": 19,
          "end": 24
        },
        "root": "#V1930940"
      }
    ],
    [
      {
        "V1931019": {
          "id": "V1931019",
          "indicator": "SPEECHACT",
          "type": "SA_TELL",
          "word": null,
          "roles": {
            "CONTENT": "#V1929860",
            "LEX": "WERE"
          },
          "start": 0,
          "end": 35
        },
        "V1929860": {
          "id": "V1929860",
          "indicator": "F",
          "type": "BE",
          "word": "BE",
          "roles": {
            "NEUTRAL": "#V1929852",
            "NEUTRAL1": "#V1929934",
            "AFFECTED-RESULT": "#V1930411",
            "TENSE": "PAST",
            "LEX": "WERE",
            "WNSENSE": "be%2:42:06::"
          },
          "start": 0,
          "end": 35
        },
        "V1930411": {
          "id": "V1930411",
          "indicator": "F",
          "type": "RECIPIENT",
          "word": "IOBJ",
          "roles": {
            "GROUND": "#V1929912",
            "FIGURE": "#V1929860"
          },
          "start": 0,
          "end": 35
        },
        "V1929852": {
          "id": "V1929852",
          "indicator": "PRO-SET",
          "type": "REFERENTIAL-SEM",
          "word": "THEY",
          "roles": {
            "PROFORM": "THEY",
            "LEX": "THEY",
            "WNSENSE": "entity%1:03:00"
          },
          "start": 0,
          "end": 5
        },
        "V1929912": {
          "id": "V1929912",
          "indicator": "A",
          "type": "FAMILY-GROUP",
          "word": "FAMILY",
          "roles": {
            "LEX": "FAMILY",
            "WNSENSE": "family%1:14:02::"
          },
          "start": 10,
          "end": 19
        },
        "V1929934": {
          "id": "V1929934",
          "indicator": "INDEF-SET",
          "type": "GAME",
          "word": "GAME",
          "roles": {
            "MOD": "#V1929959",
            "LEX": "GAMES",
            "WNSENSE": "game%1:04:00::"
          },
          "start": 19,
          "end": 35
        },
        "V1929959": {
          "id": "V1929959",
          "indicator": "F",
          "type": "STATE-RESULTING-FROM",
          "word": null,
          "roles": {
            "FIGURE": "#V1929934",
            "GROUND": "#V1929929",
            "DEGREE": "#V1929921",
            "LEX": "LOVED"
          },
          "start": 19,
          "end": 30
        },
        "V1929929": {
          "id": "V1929929",
          "indicator": "F",
          "type": "APPRECIATE",
          "word": "LOVE",
          "roles": {
            "NEUTRAL": "#V1929934",
            "WNSENSE": "love%2:37:00::"
          },
          "start": 19,
          "end": 30
        },
        "V1929921": {
          "id": "V1929921",
          "indicator": "F",
          "type": "DEGREE-MODIFIER-HIGH",
          "word": "THAT",
          "roles": {
            "FIGURE": "#V1929959",
            "LEX": "THAT",
            "WNSENSE": "profusely%4:02:00"
          },
          "start": 19,
          "end": 24
        },
        "root": "#V1931019"
      }
    ]
  ],
  "annotation": {
    "judge": "abhatia",
    "parser": "STEP",
    "timestamp": "20190820T170539",
    "link": "http://trips.ihmc.us/parser/saved/20190820T170539-STEP-abhatia-0-They_were_a_family_that_loved_games_.xml",
    "judgement": 0
  }
}